[
  {
    "AircraftId": 0,
    "Name": "F14",
    "Nickname": "Tomcat",
    "FirstFlight": 1970,
    "Introduction": 1974,
    "CombatSpeed": 10,
    "CruiseSpeed": 4,
    "CombatFuelConsumption": 4,
    "CruiseFuelConsumption": 0,
    "Fuel": 20,
    "MaxAltitude": 5,
    "Dogfighting": 7,
    "Configurations": [
      {
        "ConfigurationName": "Default",
        "WeaponSystems": [
          {
            "WeaponSystemName": "Tank500",
            "Category": "DropTank"
          },
          {
            "WeaponSystemName": "Tank500",
            "Category": "DropTank"
          },
          {
            "WeaponSystemName": "Aim-7",
            "Category": "A2A"
          },
          {
            "WeaponSystemName": "Aim-7",
            "Category": "A2A"
          }
        ]
      }
    ],
    "MaintenanceTime": 5,
    "StructuralDefense": 0,
    "MaxHitpoints": 0
  }
]
